{"name":"As a user, I can login with valid credentials","id":"login;as-a-user--i-can-login-with-valid-credentials","scenarioId":"api/Authentication/Login:As a user, I can login with valid credentials","methodName":"As a user, I can login with valid credentials","testSteps":[{"number":1,"description":"Given I set API endpoint for login","duration":645,"startTime":"2024-05-11T23:22:47.945681+07:00[Asia/Jakarta]","result":"SUCCESS","precondition":false,"level":0},{"number":2,"description":"When I login with valid credentials","duration":8302,"startTime":"2024-05-11T23:22:48.596340+07:00[Asia/Jakarta]","result":"SUCCESS","precondition":false,"level":0,"children":[{"number":3,"description":"I login with valid credentials","duration":8287,"startTime":"2024-05-11T23:22:48.606442+07:00[Asia/Jakarta]","result":"SUCCESS","precondition":false,"level":1,"children":[{"number":4,"description":"POST https://altashop-api.fly.dev/api/auth/login","duration":0,"startTime":"2024-05-11T23:22:56.892771+07:00[Asia/Jakarta]","result":"SUCCESS","restQuery":{"method":"POST","path":"https://altashop-api.fly.dev/api/auth/login","content":"{\n    \"password\": \"magnetic\",\n    \"email\": \"youyou@mail.com\"\n}","contentType":"application/json","requestHeaders":"Accept\u003d*/*\n\t\t\t\tContent-Type\u003dapplication/json","requestCookies":"","responseHeaders":"content-type: application/json\ndate: Sat, 11 May 2024 16:22:57 GMT\ncontent-encoding: gzip\ntransfer-encoding: chunked\nserver: Fly/00e000b6 (2024-05-10)\nvia: 1.1 fly.io\nfly-request-id: 01HXM7DWTZ4WDTX3FGR0W19MNZ-sin","responseCookies":"","responseBody":"{\n    \"data\": \"eyJhbGciOiJIUzI1NiIsInR5cCI6IkpXVCJ9.eyJGdWxsbmFtZSI6ImlsbGl0IiwiRW1haWwiOiJ5b3V5b3VAbWFpbC5jb20ifQ.hpmJQDqjAXuioN6D28U0EFg53-_3z0wMGVE0syo97wg\"\n}","statusCode":200},"precondition":false,"level":2}]}]},{"number":5,"description":"Then I receive status code 200","duration":71,"startTime":"2024-05-11T23:22:56.900003+07:00[Asia/Jakarta]","result":"SUCCESS","precondition":false,"level":0,"children":[{"number":6,"description":"I receive status code 200","duration":45,"startTime":"2024-05-11T23:22:56.922707+07:00[Asia/Jakarta]","result":"SUCCESS","precondition":false,"level":1}]},{"number":7,"description":"And I receive token","duration":847,"startTime":"2024-05-11T23:22:56.972560+07:00[Asia/Jakarta]","result":"SUCCESS","precondition":false,"level":0,"children":[{"number":8,"description":"I receive token","duration":842,"startTime":"2024-05-11T23:22:56.974421+07:00[Asia/Jakarta]","result":"SUCCESS","precondition":false,"level":1}]}],"userStory":{"id":"api/Authentication/Login","storyName":"Login","displayName":"Login","path":"api/Authentication/Login","pathElements":[{"name":"api","description":""},{"name":"Authentication","description":""},{"name":"Login","description":""}],"narrative":"  As a user\n  I want to login\n  So that i can have all access to all endpoint","type":"feature"},"title":"As a user, I can login with valid credentials","description":"","startTime":"2024-05-11T23:22:47.914058+07:00[Asia/Jakarta]","duration":675,"projectKey":"","isManualTestingUpToDate":false,"manual":false,"testSource":"Cucumber","order":0,"result":"SUCCESS"}